discord_toolkit/__init__.py
discord_toolkit/main.py
discord_toolkit-0.2.57.dist-info/METADATA
discord_toolkit-0.2.57.dist-info/WHEEL
discord_toolkit-0.2.57.dist-info/top_level.txt
discord_toolkit-0.2.57.dist-info/RECORD
