Metadata-Version: 2.1
Name: discord-toolkit
Version: 0.2.57
Keywords: python,discord,discord tools,discord captcha,discord cloudflare
Requires-Dist: requests
Requires-Dist: wmi
